Metadata-Version: 1.0
Name: proxx
Version: 1.0.0
Summary: UNKNOWN
Home-page: https://github.com/chris17453/proxx/
Author: Charles Watkins
Author-email: charles@titandws.com
License: Creative Commons Attribution-Noncommercial-Share Alike license
Platform: UNKNOWN
